Metadata-Version: 2.1
Name: purgatory
Version: 3.0.1
Summary: A circuit breaker implementation for asyncio
Author-Email: Guillaume Gauvrit <guillaume@gauvr.it>
License: MIT
Classifier: License :: OSI Approved :: MIT License
Classifier: Topic :: Internet :: WWW/HTTP
Classifier: Topic :: Software Development :: Libraries
Classifier: Topic :: System :: Monitoring
Classifier: Intended Audience :: Developers
Classifier: Intended Audience :: Information Technology
Classifier: Topic :: System :: Networking
Classifier: Topic :: Software Development :: Libraries :: Python Modules
Classifier: Framework :: AsyncIO
Classifier: Operating System :: OS Independent
Classifier: Environment :: Console
Classifier: Typing :: Typed
Classifier: Development Status :: 5 - Production/Stable
Project-URL: Homepage, https://github.com/mardiros/purgatory
Project-URL: Documentation, https://mardiros.github.io/purgatory
Project-URL: Repository, https://github.com/mardiros/purgatory.git
Project-URL: Issues, https://github.com/mardiros/purgatory/issues
Project-URL: Changelog, https://mardiros.github.io/purgatory/user/changelog.html
Requires-Python: >=3.9
Provides-Extra: redis
Requires-Dist: redis<6,>=5.2.0; extra == "redis"
